migrations_git_conflicts/__init__.py
migrations_git_conflicts/apps.py
migrations_git_conflicts/management/__init__.py
migrations_git_conflicts/management/commands/__init__.py
migrations_git_conflicts/management/commands/makemigrations.py
django_migrations_git_conflicts-1.0.dist-info/LICENSE
django_migrations_git_conflicts-1.0.dist-info/METADATA
django_migrations_git_conflicts-1.0.dist-info/WHEEL
django_migrations_git_conflicts-1.0.dist-info/top_level.txt
django_migrations_git_conflicts-1.0.dist-info/RECORD
